django_acquiring/__init__.py
django_acquiring/settings.py
django_acquiring/events/__init__.py
django_acquiring/events/admin.py
django_acquiring/events/apps.py
django_acquiring/events/domain.py
django_acquiring/events/models.py
django_acquiring/events/migrations/0001_initial.py
django_acquiring/events/migrations/__init__.py
django_acquiring/flows/__init__.py
django_acquiring/flows/admin.py
django_acquiring/flows/apps.py
django_acquiring/flows/models.py
django_acquiring/flows/domain/__init__.py
django_acquiring/flows/domain/blocks.py
django_acquiring/flows/domain/decision_logic.py
django_acquiring/flows/domain/flow.py
django_acquiring/flows/migrations/__init__.py
django_acquiring/payments/__init__.py
django_acquiring/payments/admin.py
django_acquiring/payments/apps.py
django_acquiring/payments/domain.py
django_acquiring/payments/models.py
django_acquiring/payments/repositories.py
django_acquiring/payments/migrations/0001_initial.py
django_acquiring/payments/migrations/__init__.py
django_acquiring/protocols/__init__.py
django_acquiring/protocols/events.py
django_acquiring/protocols/flows.py
django_acquiring/protocols/payments.py
django_acquiring/protocols/repositories.py
django_acquiring-0.1.1.dist-info/LICENSE
django_acquiring-0.1.1.dist-info/WHEEL
django_acquiring-0.1.1.dist-info/METADATA
django_acquiring-0.1.1.dist-info/RECORD
