Metadata-Version: 2.1
Name: django-acquiring
Version: 0.1.1
Summary: Django Acquiring
Author: Alvaro Duran
Requires-Python: >=3.7
Classifier: License :: OSI Approved :: MIT License
Project-URL: Home, https://github.com/acquiringlabs/django-acquiring
